moat/mqtt/__init__.py
moat/mqtt/_cfg.yaml
moat/mqtt/_main.py
moat/mqtt/adapters.py
moat/mqtt/broker.py
moat/mqtt/client.py
moat/mqtt/codecs.py
moat/mqtt/errors.py
moat/mqtt/moat_kv_broker.py
moat/mqtt/session.py
moat/mqtt/test.py
moat/mqtt/utils.py
moat/mqtt/version.py
moat/mqtt/mqtt/__init__.py
moat/mqtt/mqtt/connack.py
moat/mqtt/mqtt/connect.py
moat/mqtt/mqtt/constants.py
moat/mqtt/mqtt/disconnect.py
moat/mqtt/mqtt/packet.py
moat/mqtt/mqtt/pingreq.py
moat/mqtt/mqtt/pingresp.py
moat/mqtt/mqtt/puback.py
moat/mqtt/mqtt/pubcomp.py
moat/mqtt/mqtt/publish.py
moat/mqtt/mqtt/pubrec.py
moat/mqtt/mqtt/pubrel.py
moat/mqtt/mqtt/suback.py
moat/mqtt/mqtt/subscribe.py
moat/mqtt/mqtt/unsuback.py
moat/mqtt/mqtt/unsubscribe.py
moat/mqtt/mqtt/protocol/__init__.py
moat/mqtt/mqtt/protocol/broker_handler.py
moat/mqtt/mqtt/protocol/client_handler.py
moat/mqtt/mqtt/protocol/handler.py
moat/mqtt/plugins/__init__.py
moat/mqtt/plugins/authentication.py
moat/mqtt/plugins/logging.py
moat/mqtt/plugins/manager.py
moat/mqtt/plugins/persistence.py
moat/mqtt/plugins/topic_checking.py
moat/mqtt/plugins/sys/__init__.py
moat/mqtt/plugins/sys/broker.py
moat_mqtt-0.42.14.dist-info/licenses/LICENSE.txt
moat_mqtt-0.42.14.dist-info/METADATA
moat_mqtt-0.42.14.dist-info/WHEEL
moat_mqtt-0.42.14.dist-info/top_level.txt
moat_mqtt-0.42.14.dist-info/RECORD
