Metadata-Version: 2.4
Name: moat-mqtt
Version: 0.42.14
Summary: Async MQTT broker and client, with optional MoaT-KV support
Author-email: Matthias Urlichs <matthias@urlichs.de>
Project-URL: homepage, https://m-o-a-t.org
Project-URL: repository, https://github.com/M-o-a-T/moat
Keywords: MoaT
Classifier: Intended Audience :: Developers
Classifier: Programming Language :: Python :: 3
Classifier: Framework :: AsyncIO
Classifier: Framework :: Trio
Classifier: Framework :: AnyIO
Classifier: Development Status :: 4 - Beta
Classifier: Topic :: Communications
Classifier: Topic :: Internet
Requires-Python: >=3.8
License-File: LICENSE.txt
Requires-Dist: anyio~=4.2
Requires-Dist: transitions
Requires-Dist: asyncwebsockets>=0.9.2
Requires-Dist: passlib
Requires-Dist: attrs>=19
Requires-Dist: simplejson
Requires-Dist: msgpack
Requires-Dist: moat-util~=0.61.1
Requires-Dist: transitions
Requires-Dist: wsproto
Requires-Dist: asyncscope>=0.6.0
Requires-Dist: moat-lib-codec~=0.4.9
Requires-Dist: moat-lib-config~=0.1.0
Dynamic: license-file
